atc53/__init__.py
atc53/endpoint.py
atc53/rule/__init__.py
atc53/rule/failover.py
atc53/rule/geolocation.py
atc53/rule/geoproximity.py
atc53/rule/latency.py
atc53/rule/multivalue.py
atc53/rule/weighted.py
atc53-0.1.0.dist-info/METADATA
atc53-0.1.0.dist-info/RECORD
atc53-0.1.0.dist-info/WHEEL
atc53-0.1.0.dist-info/top_level.txt
tests/__init__.py
tests/test_endpoint.py
tests/test_failover_rule.py
tests/test_policy_document.py
tests/test_weighted_rule.py
