Metadata-Version: 2.1
Name: atc53
Version: 0.1.0
Summary: AWS Traffic Policy Document creation library
Home-page: https://github.com/cloudtools/atc53
Author: Tony Tiger
Author-email: thatrascaltiger@gmail.com
License: New BSD license
Platform: UNKNOWN
